tradestation_python_client/__init__.py
tradestation_python_client/auth.py
tradestation_python_client/base_client.py
tradestation_python_client/client.py
tradestation_python_client/toolbox.py
tradestation_python_client/endpoints/__init__.py
tradestation_python_client/endpoints/broker.py
tradestation_python_client/endpoints/mkt_data.py
tradestation_python_client/endpoints/ts_stream.py
tradestation_python_client-0.1.7.dist-info/METADATA
tradestation_python_client-0.1.7.dist-info/WHEEL
tradestation_python_client-0.1.7.dist-info/top_level.txt
tradestation_python_client-0.1.7.dist-info/RECORD
