Metadata-Version: 2.4
Name: tradestation-python-client
Version: 0.1.7
Summary: Python package for interacting with TradeStation APIs.
Author: Lorenzo Santarsieri
License: MIT
Requires-Python: >=3.10
Requires-Dist: pandas==2.3.3
Requires-Dist: python-dotenv==1.2.1
Requires-Dist: requests==2.32.5
Requires-Dist: rich==14.2.0
